Dio_package_house_rocket_project/__init__.py
Dio_package_house_rocket_project/house_rocket_project.py
Dio_package_house_rocket_project-0.0.1.dist-info/METADATA
Dio_package_house_rocket_project-0.0.1.dist-info/WHEEL
Dio_package_house_rocket_project-0.0.1.dist-info/top_level.txt
Dio_package_house_rocket_project-0.0.1.dist-info/RECORD
