Metadata-Version: 2.1
Name: Dio-package-house-rocket-project
Version: 0.0.1
Summary: Real estate sales recomnendation project
Home-page: https://github.com/frmoriya/house-rocket-project.git
Author: Francisco Moriya
Author-email: frmoriya@gmail.com
License: UNKNOWN
Platform: UNKNOWN
Requires-Python: >=3.9
